kube_cli/__init__.py
kube_cli/__main__.py
kube_cli/main.py
kube_cli-0.0.7.dist-info/LICENSE
kube_cli-0.0.7.dist-info/METADATA
kube_cli-0.0.7.dist-info/WHEEL
kube_cli-0.0.7.dist-info/entry_points.txt
kube_cli-0.0.7.dist-info/top_level.txt
kube_cli-0.0.7.dist-info/RECORD
