Metadata-Version: 2.1
Name: kube-cli
Version: 0.0.7
Summary: CLI for Kubernetes that simplifies usage of kubectl
Home-page: https://github.com/deniskrumko/kube-cli
Author: Denis Krumko
Author-email: dkrumko@gmail.com
License: MIT
Keywords: CLI,Kubernetes
Platform: UNKNOWN
Classifier: Development Status :: 4 - Beta
Classifier: Intended Audience :: Developers
Classifier: Natural Language :: English
Classifier: Environment :: Console
Classifier: License :: OSI Approved :: MIT License
Classifier: Programming Language :: Python
Classifier: Programming Language :: Python :: 3
Classifier: Programming Language :: Python :: 3.6
Classifier: Programming Language :: Python :: 3.7
Classifier: Programming Language :: Python :: 3.8
Classifier: Programming Language :: Python :: Implementation :: CPython
Classifier: Topic :: Software Development :: Libraries
Classifier: Topic :: Utilities
Requires-Python: >=3.6
